yt2mp4/__init__.py
yt2mp4/__main__.py
yt2mp4-1.0.5.dist-info/LICENSE
yt2mp4-1.0.5.dist-info/METADATA
yt2mp4-1.0.5.dist-info/WHEEL
yt2mp4-1.0.5.dist-info/entry_points.txt
yt2mp4-1.0.5.dist-info/top_level.txt
yt2mp4-1.0.5.dist-info/RECORD
