Metadata-Version: 2.1
Name: yt2mp4
Version: 1.0.5
Summary: Download YouTube videos and playlists as MP4 files (and other formats)
Home-page: https://github.com/donno2048/yt2mp4
Author: Elisha Hollander
Author-email: just4now666666@gmail.com
License: MIT
Project-URL: Documentation, https://github.com/donno2048/yt2mp4#readme
Project-URL: Bug Reports, https://github.com/donno2048/yt2mp4/issues
Project-URL: Source Code, https://github.com/donno2048/yt2mp4
Platform: UNKNOWN
Classifier: Programming Language :: Python :: 3
Requires-Python: >=3.0
License-File: LICENSE
Requires-Dist: selenium (>=4.1.0)
Requires-Dist: selenium-wire (>=4.5.6)
Requires-Dist: moviepy (>=1.0.3)
